obsidian_mcp/client.py
obsidian_mcp/search.py
obsidian_mcp/server.py
obsidian_mcp/utils.py
obsidian_api_mcp_server-1.0.1.dist-info/METADATA
obsidian_api_mcp_server-1.0.1.dist-info/WHEEL
obsidian_api_mcp_server-1.0.1.dist-info/entry_points.txt
obsidian_api_mcp_server-1.0.1.dist-info/licenses/LICENSE
obsidian_api_mcp_server-1.0.1.dist-info/RECORD
