Metadata-Version: 2.4
Name: obsidian-api-mcp-server
Version: 1.0.1
Summary: MCP server enabling AI agents to perform natural knowledge discovery and analysis across Obsidian vaults
Author-email: pmmvr <17574355+pmmvr@users.noreply.github.com>
License: MIT
License-File: LICENSE
Keywords: ai,knowledge-management,mcp,obsidian,rest-api
Classifier: Development Status :: 4 - Beta
Classifier: Intended Audience :: Developers
Classifier: License :: OSI Approved :: MIT License
Classifier: Programming Language :: Python :: 3
Classifier: Programming Language :: Python :: 3.10
Classifier: Programming Language :: Python :: 3.11
Classifier: Programming Language :: Python :: 3.12
Classifier: Topic :: Office/Business :: Groupware
Classifier: Topic :: Software Development :: Libraries :: Python Modules
Classifier: Topic :: Text Processing :: General
Requires-Python: >=3.10
Requires-Dist: httpx>=0.27.0
Requires-Dist: mcp>=1.9.1
Requires-Dist: mcp[cli]
Requires-Dist: pydantic>=2.0.0
Requires-Dist: python-dateutil>=2.9.0
Requires-Dist: python-dotenv>=1.0.0
Provides-Extra: test
Requires-Dist: behave>=1.2.6; extra == 'test'
Requires-Dist: pytest-mock>=3.12.0; extra == 'test'
Requires-Dist: responses>=0.24.0; extra == 'test'
